videogen_hub/__init__.py
videogen_hub/_version.py
videogen_hub/depend/__init__.py
videogen_hub/depend/icetk/__init__.py
videogen_hub/depend/icetk/ice_tokenizer.py
videogen_hub/depend/icetk/image_tokenizer.py
videogen_hub/depend/icetk/sentencepiece_model_pb2.py
videogen_hub/depend/icetk/text_tokenizer.py
videogen_hub/depend/icetk/utils.py
videogen_hub/depend/icetk/vqvae/__init__.py
videogen_hub/depend/icetk/vqvae/api.py
videogen_hub/depend/icetk/vqvae/enc_dec.py
videogen_hub/depend/icetk/vqvae/quantize.py
videogen_hub/depend/icetk/vqvae/vqvae_hierarchical.py
videogen_hub/infermodels/__init__.py
videogen_hub/infermodels/cogvideo.py
videogen_hub/infermodels/consisti2v.py
videogen_hub/infermodels/dynamicrafter.py
videogen_hub/infermodels/i2vgen_xl.py
videogen_hub/infermodels/lavie.py
videogen_hub/infermodels/modelscope.py
videogen_hub/infermodels/opensora.py
videogen_hub/infermodels/opensora_12.py
videogen_hub/infermodels/opensora_plan.py
videogen_hub/infermodels/seine.py
videogen_hub/infermodels/show_one.py
videogen_hub/infermodels/streamingt2v.py
videogen_hub/infermodels/t2v_turbo.py
videogen_hub/infermodels/videocrafter.py
videogen_hub/metrics/__init__.py
videogen_hub/pipelines/__init__.py
videogen_hub/pipelines/cogvideo/__init__.py
videogen_hub/pipelines/cogvideo/cogvideo_pipeline.py
videogen_hub/pipelines/dynamicrafter/__init__.py
videogen_hub/pipelines/dynamicrafter/inference.py
videogen_hub/pipelines/dynamicrafter/utils.py
videogen_hub/pipelines/opensora/__init__.py
videogen_hub/pipelines/opensora/opensora/__init__.py
videogen_hub/pipelines/opensora/opensora/registry.py
videogen_hub/pipelines/opensora/opensora/acceleration/__init__.py
videogen_hub/pipelines/opensora/opensora/acceleration/checkpoint.py
videogen_hub/pipelines/opensora/opensora/acceleration/communications.py
videogen_hub/pipelines/opensora/opensora/acceleration/parallel_states.py
videogen_hub/pipelines/opensora/opensora/acceleration/plugin.py
videogen_hub_comfy-0.1.2.dist-info/LICENSE
videogen_hub_comfy-0.1.2.dist-info/METADATA
videogen_hub_comfy-0.1.2.dist-info/WHEEL
videogen_hub_comfy-0.1.2.dist-info/top_level.txt
videogen_hub_comfy-0.1.2.dist-info/RECORD
