Metadata-Version: 2.1
Name: videogen_hub_comfy
Version: 0.1.2
Summary: VideoGenHub is a one-stop library to standardize the inference and evaluation of all the conditional video generation models. (This is a temporary package for Comfy SVD Advanced)
Home-page: https://github.com/TIGER-AI-Lab/VideoGenHub
Author: D8ahazard, Max Kueng, and the TIGER-AI Lab team
Author-email: d8ahazard@gmail.com
License: MIT License
Classifier: Development Status :: 4 - Beta
Classifier: Environment :: GPU :: NVIDIA CUDA
Classifier: Intended Audience :: Developers
Classifier: Intended Audience :: Education
Classifier: Intended Audience :: Science/Research
Classifier: Operating System :: OS Independent
Classifier: Topic :: Scientific/Engineering :: Artificial Intelligence
Classifier: Programming Language :: Python :: 3
License-File: LICENSE
